{
      "name": "#6148",
      "description": "The IMX Punks is a collection of 10,000 unique Punks with varying rarity and style. The First algorithmically generated digital collection of diverse Punk NFTs chilling on the Immutable X, a Layer 2 for NFTs on Ethereum. Each character is impeccably designed, thoughtfully picked, and super funky! #PunkItUp",
      "image_url": "https://gateway.pinata.cloud/ipfs/QmeiBY7au5KDwoFkX3MQktwSjSL4XgBCxRFEvCEMYBr8Tt",
      "Type": "Human",
      "Skin": "Mid",
      "Ear": "None",
      "Head/Hat": "Blue Band",
      "Mouth": "Straight",
      "Nose": "Normal",
      "Mole": "None",
      "Beard": "Normal Beard Brown",
      "Mouth Accessories": "Vape Blue",
      "Eyewear": "Purple Square Glasses",
      "Neck Accessories": "None"
}